<annotation>
	<folder>images</folder>
	<filename>307.jpg</filename>
	<path>C:\Users\Ross\Desktop\Literally Everything Part 2 - Battle Tendency\darkflow-master\images\307.jpg</path>
	<source>
		<database>Unknown</database>
	</source>
	<size>
		<width>320</width>
		<height>240</height>
		<depth>3</depth>
	</size>
	<segmented>0</segmented>
	<object>
		<name>power_cell</name>
		<pose>Unspecified</pose>
		<truncated>0</truncated>
		<difficult>0</difficult>
		<bndbox>
			<xmin>121</xmin>
			<ymin>72</ymin>
			<xmax>178</xmax>
			<ymax>143</ymax>
		</bndbox>
	</object>
	<object>
		<name>power_cell</name>
		<pose>Unspecified</pose>
		<truncated>0</truncated>
		<difficult>0</difficult>
		<bndbox>
			<xmin>167</xmin>
			<ymin>91</ymin>
			<xmax>224</xmax>
			<ymax>162</ymax>
		</bndbox>
	</object>
	<object>
		<name>power_cell</name>
		<pose>Unspecified</pose>
		<truncated>0</truncated>
		<difficult>0</difficult>
		<bndbox>
			<xmin>212</xmin>
			<ymin>140</ymin>
			<xmax>269</xmax>
			<ymax>211</ymax>
		</bndbox>
	</object>
</annotation>
